nonebot_plugin_sunoai/__init__.py
nonebot_plugin_sunoai/config.py
nonebot_plugin_sunoai-0.1.0.dist-info/LICENSE
nonebot_plugin_sunoai-0.1.0.dist-info/METADATA
nonebot_plugin_sunoai-0.1.0.dist-info/WHEEL
nonebot_plugin_sunoai-0.1.0.dist-info/RECORD
