Metadata-Version: 2.1
Name: nonebot-plugin-sunoai
Version: 0.1.0
Summary: 基于第三方柏拉图api的sunoai插件，支持文生音乐和纯音乐
Home-page: https://github.com/CCYellowStar2/nonebot-plugin-sunoai
License: GPL-3.0-only
Author: CCYellowStar
Requires-Python: >=3.9,<4
Classifier: License :: OSI Approved :: GNU General Public License v3 (GPLv3)
Classifier: Programming Language :: Python :: 3
Classifier: Programming Language :: Python :: 3.9
Classifier: Programming Language :: Python :: 3.10
Classifier: Programming Language :: Python :: 3.11
Classifier: Programming Language :: Python :: 3.12
Requires-Dist: aiohttp (>=3.8.4)
Requires-Dist: arclet-alconna (>=1.8.20)
Requires-Dist: nonebot-plugin-alconna (>=0.50.2)
Requires-Dist: nonebot2 (>=2.3.0)
Project-URL: Repository, https://github.com/CCYellowStar2/nonebot-plugin-sunoai
